bibliofabric/__init__.py
bibliofabric/auth.py
bibliofabric/client.py
bibliofabric/config.py
bibliofabric/exceptions.py
bibliofabric/log_config.py
bibliofabric/models.py
bibliofabric/resources.py
bibliofabric/types.py
bibliofabric-0.1.0.dist-info/METADATA
bibliofabric-0.1.0.dist-info/WHEEL
bibliofabric-0.1.0.dist-info/RECORD
