Metadata-Version: 2.4
Name: bibliofabric
Version: 0.1.0
Summary: Generic framework for building modern asynchronous API clients for bibliometric and scholarly data retrieval
Project-URL: Homepage, https://github.com/utsmok/bibliofabric
Author-email: Samuel Mok <s.mok@utwente.nl>
License: MIT
Requires-Python: >=3.12
Requires-Dist: cachetools>=5.3.0
Requires-Dist: httpx>=0.27.0
Requires-Dist: loguru>=0.7.0
Requires-Dist: pydantic-settings>=2.9.1
Requires-Dist: pydantic>=2.9.0
Requires-Dist: python-dotenv>=1.1.0
Requires-Dist: tenacity>=9.1.2
